LICENSE
MANIFEST.in
README.md
setup.py
mundiapi/__init__.py
mundiapi/api_helper.py
mundiapi/configuration.py
mundiapi/decorators.py
mundiapi/mundiapi_client.py
mundiapi.egg-info/PKG-INFO
mundiapi.egg-info/SOURCES.txt
mundiapi.egg-info/dependency_links.txt
mundiapi.egg-info/requires.txt
mundiapi.egg-info/top_level.txt
mundiapi/controllers/__init__.py
mundiapi/controllers/base_controller.py
mundiapi/controllers/charges_controller.py
mundiapi/controllers/customers_controller.py
mundiapi/controllers/invoices_controller.py
mundiapi/controllers/orders_controller.py
mundiapi/controllers/plans_controller.py
mundiapi/controllers/recipients_controller.py
mundiapi/controllers/sellers_controller.py
mundiapi/controllers/subscriptions_controller.py
mundiapi/controllers/tokens_controller.py
mundiapi/controllers/transactions_controller.py
mundiapi/controllers/transfers_controller.py
mundiapi/exceptions/__init__.py
mundiapi/exceptions/api_exception.py
mundiapi/exceptions/error_exception.py
mundiapi/http/__init__.py
mundiapi/http/http_call_back.py
mundiapi/http/http_client.py
mundiapi/http/http_context.py
mundiapi/http/http_method_enum.py
mundiapi/http/http_request.py
mundiapi/http/http_response.py
mundiapi/http/requests_client.py
mundiapi/http/auth/__init__.py
mundiapi/http/auth/basic_auth.py
mundiapi/models/__init__.py
mundiapi/models/address.py
mundiapi/models/address_1.py
mundiapi/models/apple_pay.py
mundiapi/models/authentication.py
mundiapi/models/authentication_2.py
mundiapi/models/bank_account.py
mundiapi/models/bank_account_1.py
mundiapi/models/bank_transfer.py
mundiapi/models/bank_transfer_1.py
mundiapi/models/bank_transfer_2.py
mundiapi/models/billing_address.py
mundiapi/models/billing_address_1.py
mundiapi/models/billingaddress_3.py
mundiapi/models/boleto_1.py
mundiapi/models/cancel_split_request.py
mundiapi/models/card.py
mundiapi/models/card_1.py
mundiapi/models/card_11.py
mundiapi/models/card_9.py
mundiapi/models/charge.py
mundiapi/models/charges_capture_request.py
mundiapi/models/charges_capture_response.py
mundiapi/models/charges_card_request.py
mundiapi/models/charges_card_response.py
