Metadata-Version: 1.0
Name: mundiapi
Version: 2.4.2
Summary: Mundipagg API
Home-page: https://github.com/mundipagg/MundiAPI-PYTHON
Author: Mundipagg
Author-email: suporte@mundipagg.com
License: UNKNOWN
Platform: UNKNOWN
